{
  "appPageId" : "daf6072e-062f-4d1d-8087-61f4087b74f0",
  "componentName" : "siteforce:sldsOneColLayout",
  "id" : "5737a581-c0e0-48da-8e41-103f93539880",
  "label" : "Account Management",
  "regions" : [ {
    "id" : "db4220d3-a65b-443d-aca8-ea8c566a776d",
    "regionName" : "header",
    "type" : "region"
  }, {
    "components" : [ {
      "componentAttributes" : {
        "tabsetConfig" : {
          "UUID" : "5f4500cb-c366-4757-b65a-6bd91bdcf7e5",
          "activeTab" : "tab1",
          "useOverflowMenu" : false,
          "tabs" : [ {
            "UUID" : "52ca6fec-dd2f-411b-a9fa-dad178c79077",
            "tabName" : "Members",
            "tabKey" : "tab1",
            "locked" : false,
            "allowGuestUser" : false,
            "seedComponents" : [ {
              "fqn" : "forceCommunity:relatedList",
              "attributes" : {
                "parentRecordId" : "{!CurrentUser.accountId}",
                "relatedListName" : "Users",
                "customTitle" : "Members",
                "showCustomTitle" : "true",
                "showBreadCrumbs" : "false",
                "showRowNumbers" : "false",
                "showManualRefreshButton" : "false"
              }
            } ]
          }, {
            "UUID" : "7355bb7f-fcea-4e1c-93d3-ccbdbd8dfda5",
            "tabName" : "Branding",
            "tabKey" : "tab2",
            "locked" : false,
            "allowGuestUser" : false,
            "seedComponents" : [ {
              "fqn" : "forceCommunity:accountBrandRecord",
              "attributes" : {
                "recordId" : "{!CurrentUser.accountId}"
              }
            } ]
          } ]
        }
      },
      "componentName" : "forceCommunity:tabset",
      "id" : "5f4500cb-c366-4757-b65a-6bd91bdcf7e5",
      "regions" : [ {
        "components" : [ {
          "componentAttributes" : {
            "customTitle" : "Members",
            "parentRecordId" : "{!CurrentUser.accountId}",
            "relatedListName" : "Users",
            "showBreadCrumbs" : false,
            "showCustomTitle" : true,
            "showManualRefreshButton" : false,
            "showRowNumbers" : false
          },
          "componentName" : "forceCommunity:relatedList",
          "id" : "d544c10c-53ef-4c37-bb75-53e875a7a397",
          "renditionMap" : { },
          "type" : "component"
        } ],
        "id" : "52ca6fec-dd2f-411b-a9fa-dad178c79077",
        "regionLabel" : "Members",
        "regionName" : "tab1",
        "renditionMap" : { },
        "type" : "region"
      }, {
        "components" : [ {
          "componentAttributes" : {
            "recordId" : "{!CurrentUser.accountId}"
          },
          "componentName" : "forceCommunity:accountBrandRecord",
          "id" : "968c2819-672b-48c3-b1e2-969c28169cee",
          "renditionMap" : { },
          "type" : "component"
        } ],
        "id" : "7355bb7f-fcea-4e1c-93d3-ccbdbd8dfda5",
        "regionLabel" : "Branding",
        "regionName" : "tab2",
        "renditionMap" : { },
        "type" : "region"
      } ],
      "renderPriority" : "NEUTRAL",
      "renditionMap" : { },
      "type" : "component"
    } ],
    "id" : "00025abb-c6e6-4de2-b8e2-279e2c69ecf6",
    "regionName" : "content",
    "type" : "region"
  }, {
    "id" : "7be66785-9efd-4169-a155-5999533604d6",
    "regionName" : "footer",
    "type" : "region"
  }, {
    "components" : [ {
      "componentAttributes" : {
        "description" : "",
        "metaTags" : "",
        "title" : "Account Management"
      },
      "componentName" : "forceCommunity:seoAssistant",
      "id" : "41631b10-f324-4530-927b-a03a7dd5ffcd",
      "renditionMap" : { },
      "type" : "component"
    } ],
    "id" : "63a3c56d-eb5f-4a0c-a304-bf5d32ffc98c",
    "regionName" : "sfdcHiddenRegion",
    "type" : "region"
  } ],
  "themeLayoutType" : "Inner",
  "type" : "view",
  "viewType" : "account-management"
}