{
  "appPageId" : "daf6072e-062f-4d1d-8087-61f4087b74f0",
  "componentName" : "siteforce:sldsOneColLayout",
  "id" : "25538561-4fe4-472f-afd9-556e64c21510",
  "label" : "Case List",
  "regions" : [ {
    "id" : "4a7814a4-e70e-41c2-967c-2326b7facf6d",
    "regionName" : "header",
    "type" : "region"
  }, {
    "components" : [ {
      "componentAttributes" : {
        "enableInlineEdit" : true,
        "filterName" : "{!filterId}",
        "layout" : "FULL",
        "pageSize" : 25,
        "scope" : "{!objectName}",
        "showActionBar" : true,
        "showChartsPanel" : true,
        "showDisplay" : "showall",
        "showFilterPanel" : true,
        "showImageIcon" : true,
        "showManualRefreshButton" : true,
        "showObjectName" : true,
        "showPinnedList" : true,
        "showSearchBar" : true
      },
      "componentName" : "forceCommunity:objectHome",
      "id" : "c31f1811-0754-4261-9f3b-6f9691389736",
      "renderPriority" : "NEUTRAL",
      "renditionMap" : { },
      "type" : "component"
    } ],
    "id" : "8bd192eb-4a2c-4965-a1e1-a4f9921c7b9e",
    "regionName" : "content",
    "type" : "region"
  }, {
    "id" : "0d710404-b08d-43bd-b9e9-dffcef002469",
    "regionName" : "footer",
    "type" : "region"
  } ],
  "themeLayoutType" : "Inner",
  "type" : "view",
  "viewType" : "list-500"
}